pulumi_prismasdwan/__init__.py
pulumi_prismasdwan/_utilities.py
pulumi_prismasdwan/get_site.py
pulumi_prismasdwan/provider.py
pulumi_prismasdwan/pulumi-plugin.json
pulumi_prismasdwan/py.typed
pulumi_prismasdwan/site.py
pulumi_prismasdwan/config/__init__.py
pulumi_prismasdwan/config/__init__.pyi
pulumi_prismasdwan/config/vars.py
pulumi_prismasdwan-0.1.1.dist-info/METADATA
pulumi_prismasdwan-0.1.1.dist-info/WHEEL
pulumi_prismasdwan-0.1.1.dist-info/top_level.txt
pulumi_prismasdwan-0.1.1.dist-info/RECORD
