Metadata-Version: 2.1
Name: pulumi_prismasdwan
Version: 0.1.1
Summary: A Pulumi package for managing resources for Prisma SD-WAN.
License: Apache-2.0
Project-URL: Homepage, https://www.paloaltonetworks.com/sase/sd-wan
Project-URL: Repository, https://github.com/paloaltonetworks/pulumi-prismasdwan
Keywords: pulumi,prismasdwan,paloaltonetworks,category/network
Requires-Python: >=3.8
Requires-Dist: parver >=0.2.1
Requires-Dist: pulumi <4.0.0,>=3.0.0
Requires-Dist: semver >=2.8.1
